fml2blender/__init__.py
fml2blender/build.py
fml2blender/cli.py
fml2blender/harvest.py
fml2blender-0.1.1.dist-info/licenses/LICENSE
fml2blender-0.1.1.dist-info/METADATA
fml2blender-0.1.1.dist-info/WHEEL
fml2blender-0.1.1.dist-info/entry_points.txt
fml2blender-0.1.1.dist-info/top_level.txt
fml2blender-0.1.1.dist-info/RECORD
