Metadata-Version: 2.4
Name: fml2blender
Version: 0.1.1
Summary: Convert Floorplanner FML floor plans to Blender 3D scenes
Author: David de Meij
License: MIT
Project-URL: Homepage, https://github.com/daviddemeij/fml2blender
Project-URL: Repository, https://github.com/daviddemeij/fml2blender
Project-URL: Issues, https://github.com/daviddemeij/fml2blender/issues
Keywords: floorplanner,blender,3d,floor-plan,fml
Classifier: Development Status :: 3 - Alpha
Classifier: Intended Audience :: Developers
Classifier: License :: OSI Approved :: MIT License
Classifier: Programming Language :: Python :: 3
Classifier: Programming Language :: Python :: 3.10
Classifier: Programming Language :: Python :: 3.11
Classifier: Programming Language :: Python :: 3.12
Classifier: Topic :: Multimedia :: Graphics :: 3D Modeling
Requires-Python: >=3.10
License-File: LICENSE
Requires-Dist: requests>=2.28.0
Provides-Extra: dev
Requires-Dist: pytest>=7.0; extra == "dev"
Requires-Dist: black; extra == "dev"
Requires-Dist: ruff; extra == "dev"
Dynamic: license-file
